zynapse/__init__.py
zynapse/connection.py
zynapse/frame.py
zynapse/main.py
zynapse/models.py
zynapse/tracking.py
zynapse-0.1.2.dist-info/METADATA
zynapse-0.1.2.dist-info/WHEEL
zynapse-0.1.2.dist-info/RECORD
