Metadata-Version: 2.3
Name: zynapse
Version: 0.1.2
Summary: ZkAGI SDK
Author-email: Lulzx <wiserishabh@gmail.com>
Requires-Python: >=3.8
Requires-Dist: ezkl>=10.4.2
Requires-Dist: fabric>=3.2.2
